MANIFEST.in
README.rst
setup.cfg
setup.py
PyElk/Const.py
PyElk/Elk.py
PyElk/__init__.py
PyElk.egg-info/PKG-INFO
PyElk.egg-info/SOURCES.txt
PyElk.egg-info/dependency_links.txt
PyElk.egg-info/not-zip-safe
PyElk.egg-info/requires.txt
PyElk.egg-info/top_level.txt
PyElk/Area/__init__.py
PyElk/Connection/__init__.py
PyElk/Counter/__init__.py
PyElk/Event/__init__.py
PyElk/Keypad/__init__.py
PyElk/Node/__init__.py
PyElk/Output/__init__.py
PyElk/Setting/__init__.py
PyElk/Task/__init__.py
PyElk/Thermostat/__init__.py
PyElk/User/__init__.py
PyElk/X10/__init__.py
PyElk/Zone/__init__.py