Metadata-Version: 1.1
Name: PyElk
Version: 0.2.0.dev20
Summary: Python module to talk to Elk M1 Gold and M1 EZ8 security / integration panels.
Home-page: https://github.com/BioSehnsucht/pyelk
Author: Jonathan Vaughn
Author-email: biosehnsucht+pyelk@gmail.com
License: Apache License 2.0
Platform: UNKNOWN
Classifier: Intended Audience :: Developers
Classifier: Operating System :: OS Independent
Classifier: Development Status :: 3 - Alpha
Classifier: License :: OSI Approved :: Apache Software License
Classifier: Programming Language :: Python :: 3
Classifier: Topic :: Software Development :: Libraries :: Python Modules
